django_crispy_bulma/__init__.py
django_crispy_bulma/apps.py
django_crispy_bulma/forms.py
django_crispy_bulma/layout.py
django_crispy_bulma/settings.py
django_crispy_bulma/widgets.py
django_crispy_bulma/templates/bootstrap4/accordion-group.html
django_crispy_bulma/templates/bootstrap4/accordion.html
django_crispy_bulma/templates/bootstrap4/betterform.html
django_crispy_bulma/templates/bootstrap4/display_form.html
django_crispy_bulma/templates/bootstrap4/errors.html
django_crispy_bulma/templates/bootstrap4/errors_formset.html
django_crispy_bulma/templates/bootstrap4/field.html
django_crispy_bulma/templates/bootstrap4/inputs.html
django_crispy_bulma/templates/bootstrap4/table_inline_formset.html
django_crispy_bulma/templates/bootstrap4/uni_form.html
django_crispy_bulma/templates/bootstrap4/uni_formset.html
django_crispy_bulma/templates/bootstrap4/whole_uni_form.html
django_crispy_bulma/templates/bootstrap4/whole_uni_formset.html
django_crispy_bulma/templates/bootstrap4/layout/alert.html
django_crispy_bulma/templates/bootstrap4/layout/baseinput.html
django_crispy_bulma/templates/bootstrap4/layout/button.html
django_crispy_bulma/templates/bootstrap4/layout/buttonholder.html
django_crispy_bulma/templates/bootstrap4/layout/checkboxselectmultiple.html
django_crispy_bulma/templates/bootstrap4/layout/checkboxselectmultiple_inline.html
django_crispy_bulma/templates/bootstrap4/layout/div.html
django_crispy_bulma/templates/bootstrap4/layout/field_with_buttons.html
django_crispy_bulma/templates/bootstrap4/layout/fieldset.html
django_crispy_bulma/templates/bootstrap4/layout/formactions.html
django_crispy_bulma/templates/bootstrap4/layout/help_text_and_errors.html
django_crispy_bulma/templates/bootstrap4/layout/inline_field.html
django_crispy_bulma/templates/bootstrap4/layout/multifield.html
django_crispy_bulma/templates/bootstrap4/layout/prepended_appended_text.html
django_crispy_bulma/templates/bootstrap4/layout/radioselect.html
django_crispy_bulma-0.2.dist-info/LICENCE.txt
django_crispy_bulma-0.2.dist-info/METADATA
django_crispy_bulma-0.2.dist-info/WHEEL
django_crispy_bulma-0.2.dist-info/top_level.txt
django_crispy_bulma-0.2.dist-info/RECORD
